anyrl/__init__.py
anyrl/algos/__init__.py
anyrl/algos/a2c.py
anyrl/algos/advantages.py
anyrl/algos/dqn.py
anyrl/algos/mpi.py
anyrl/algos/ppo.py
anyrl/algos/schedules.py
anyrl/algos/util.py
anyrl/envs/__init__.py
anyrl/envs/base.py
anyrl/envs/gym.py
anyrl/envs/wrappers/__init__.py
anyrl/envs/wrappers/batched.py
anyrl/envs/wrappers/image.py
anyrl/envs/wrappers/logs.py
anyrl/envs/wrappers/meta.py
anyrl/envs/wrappers/padding.py
anyrl/envs/wrappers/skip.py
anyrl/models/__init__.py
anyrl/models/base.py
anyrl/models/dqn_dist.py
anyrl/models/dqn_scalar.py
anyrl/models/feedforward_ac.py
anyrl/models/misc.py
anyrl/models/recurrent_ac.py
anyrl/models/util.py
anyrl/rollouts/__init__.py
anyrl/rollouts/list.py
anyrl/rollouts/logger.py
anyrl/rollouts/norm.py
anyrl/rollouts/players.py
anyrl/rollouts/replay.py
anyrl/rollouts/rollers.py
anyrl/rollouts/rollout.py
anyrl/rollouts/util.py
anyrl/spaces/__init__.py
anyrl/spaces/aggregate.py
anyrl/spaces/base.py
anyrl/spaces/binary.py
anyrl/spaces/categorical.py
anyrl/spaces/continuous.py
anyrl/spaces/gym.py
anyrl/tests/__init__.py
anyrl/tests/test_ac_models.py
anyrl/tests/test_advantages.py
anyrl/tests/test_algos_util.py
anyrl/tests/test_dist_q.py
anyrl/tests/test_dists.py
anyrl/tests/test_env.py
anyrl/tests/test_mpi.py
anyrl/tests/test_norm.py
anyrl/tests/test_players.py
anyrl/tests/test_replay.py
anyrl/tests/test_rollers.py
anyrl/tests/test_schedules.py
anyrl/tests/test_spaces.py
anyrl/tests/test_utils.py
anyrl/tests/test_wrappers.py
anyrl/tests/util.py
anyrl/utils/__init__.py
anyrl/utils/atomic.py
anyrl/utils/ffmpeg.py
anyrl/utils/mpi.py
anyrl/utils/ppo.py
anyrl/utils/tf_state.py
anyrl-0.12.23.dist-info/METADATA
anyrl-0.12.23.dist-info/RECORD
anyrl-0.12.23.dist-info/WHEEL
anyrl-0.12.23.dist-info/top_level.txt
