Metadata-Version: 2.1
Name: anyrl
Version: 0.12.23
Summary: A library for Reinforcement Learning
Home-page: https://github.com/unixpickle/anyrl-py
Author: Alex Nichol
Author-email: unixpickle@gmail.com
License: BSD
Keywords: ai reinforcement learning
Platform: UNKNOWN
Classifier: Development Status :: 4 - Beta
Classifier: Intended Audience :: Developers
Classifier: License :: OSI Approved :: BSD License
Classifier: Programming Language :: Python :: 3.5
Classifier: Programming Language :: Python :: 3.6
Provides-Extra: mpi
Provides-Extra: tf_gpu
Provides-Extra: tf
Requires-Dist: numpy (<2.0.0,>=1.0.0)
Requires-Dist: cloudpickle (>=0.4.0)
Requires-Dist: gym (<0.11.0,>=0.9.6)
Requires-Dist: pandas (<0.24.0,>=0.20.0)
Provides-Extra: mpi
Requires-Dist: mpi4py (<3.0.0,>=2.0.0); extra == 'mpi'
Provides-Extra: tf
Requires-Dist: tensorflow (>=1.0.0); extra == 'tf'
Provides-Extra: tf_gpu
Requires-Dist: tensorflow-gpu (>=1.0.0); extra == 'tf_gpu'
